gradient_agreement_filtering.py
gradient_agreement_filtering-0.1.3.dist-info/LICENSE
gradient_agreement_filtering-0.1.3.dist-info/METADATA
gradient_agreement_filtering-0.1.3.dist-info/WHEEL
gradient_agreement_filtering-0.1.3.dist-info/top_level.txt
gradient_agreement_filtering-0.1.3.dist-info/RECORD
