Metadata-Version: 2.1
Name: gradient_agreement_filtering
Version: 0.1.3
Summary: Gradient Agreement Filtering (GAF) Package
Author-email: Francois Chaubard <fchaubard@gmail.com>
License: MIT License
Requires-Python: >=3.7
License-File: LICENSE
Requires-Dist: torch
Requires-Dist: torchvision
Requires-Dist: numpy
